mixmil/__init__.py
mixmil/data.py
mixmil/model.py
mixmil/paths.py
mixmil/posterior.py
mixmil/simulation.py
mixmil/utils.py
mixmil-0.1.2.dist-info/METADATA
mixmil-0.1.2.dist-info/WHEEL
mixmil-0.1.2.dist-info/licenses/LICENSE
mixmil-0.1.2.dist-info/RECORD
