Metadata-Version: 2.3
Name: mixmil
Version: 0.1.2
Summary: Attention-based Multi-instance Mixed Models
Project-URL: Homepage, https://github.com/AIH-SGML/mixmil
Project-URL: Bug Tracker, https://github.com/AIH-SGML/mixmil/issues
Project-URL: Discussions, https://github.com/AIH-SGML/mixmil/discussions
Author-email: Jan Engelmann <jan.engelmann@helmholtz-munich.de>, Alessandro Palma <alessandro.palma@helmholtz-munich.de>, Paolo Casale <francescopaolo.casale@helmholtz-munich.de>
License:                                  Apache License
License-File: LICENSE
Classifier: Development Status :: 3 - Alpha
Classifier: Intended Audience :: Developers
Classifier: Intended Audience :: Science/Research
Classifier: License :: OSI Approved :: Apache Software License
Classifier: Natural Language :: English
Classifier: Operating System :: MacOS :: MacOS X
Classifier: Operating System :: Microsoft :: Windows
Classifier: Operating System :: POSIX :: Linux
Classifier: Programming Language :: Python :: 3 :: Only
Classifier: Programming Language :: Python :: 3.9
Classifier: Programming Language :: Python :: 3.10
Classifier: Programming Language :: Python :: 3.11
Classifier: Programming Language :: Python :: 3.12
Classifier: Topic :: Scientific/Engineering :: Bio-Informatics
Requires-Python: >=3.9
Requires-Dist: numpy>=1.22.0
Requires-Dist: scikit-learn>=1.3.0
Requires-Dist: scipy>=1.8.0
Requires-Dist: statsmodels>=0.11.0
Requires-Dist: torch-scatter>=2.0.1
Requires-Dist: torch>=1.4.0
Requires-Dist: tqdm>=4.0.0
Provides-Extra: all
Requires-Dist: anndata>=0.8.0; extra == 'all'
Requires-Dist: jupyterlab>=3.0.0; extra == 'all'
Requires-Dist: pytest>=6.0.0; extra == 'all'
Provides-Extra: experiments
Requires-Dist: anndata>=0.8.0; extra == 'experiments'
Requires-Dist: jupyterlab>=3.0.0; extra == 'experiments'
Provides-Extra: test
Requires-Dist: pytest>=6.0.0; extra == 'test'
